setup.py
appomatic_djangomail/__init__.py
appomatic_djangomail/admin.py
appomatic_djangomail/html2text.py
appomatic_djangomail/models.py
appomatic_djangomail.egg-info/PKG-INFO
appomatic_djangomail.egg-info/SOURCES.txt
appomatic_djangomail.egg-info/dependency_links.txt
appomatic_djangomail.egg-info/not-zip-safe
appomatic_djangomail.egg-info/top_level.txt