Metadata-Version: 1.0
Name: appomatic-djangomail
Version: 0.0.1
Summary: Django email templating system
Home-page: http://github.com/redhog/appomatic_djangomail
Author: Egil Moeller
Author-email: egil@inonit.no
License: UNKNOWN
Platform: UNKNOWN
